odoo10_addon_donation_mass-10.0.1.0.0.99.dev3-py2.7-nspkg.pth
odoo/addons/donation_mass/README.rst
odoo/addons/donation_mass/__init__.py
odoo/addons/donation_mass/__manifest__.py
odoo/addons/donation_mass/donation.py
odoo/addons/donation_mass/donation_mass_data.xml
odoo/addons/donation_mass/donation_mass_demo.xml
odoo/addons/donation_mass/donation_view.xml
odoo/addons/donation_mass/mass.py
odoo/addons/donation_mass/mass_view.xml
odoo/addons/donation_mass/product.py
odoo/addons/donation_mass/i18n/fr.po
odoo/addons/donation_mass/security/ir.model.access.csv
odoo/addons/donation_mass/static/description/icon.png
odoo/addons/donation_mass/tests/__init__.py
odoo/addons/donation_mass/tests/test_donation_mass.py
odoo/addons/donation_mass/wizard/select_mass_requests_to_transfer_view.xml
odoo10_addon_donation_mass-10.0.1.0.0.99.dev3.dist-info/METADATA
odoo10_addon_donation_mass-10.0.1.0.0.99.dev3.dist-info/RECORD
odoo10_addon_donation_mass-10.0.1.0.0.99.dev3.dist-info/WHEEL
odoo10_addon_donation_mass-10.0.1.0.0.99.dev3.dist-info/namespace_packages.txt
odoo10_addon_donation_mass-10.0.1.0.0.99.dev3.dist-info/top_level.txt
