Metadata-Version: 2.1
Name: odoo10-addon-donation-mass
Version: 10.0.1.0.0.99.dev3
Summary: Ability to create mass from donation lines
Home-page: http://www.barroux.org
Author: Barroux Abbey, Akretion, Odoo Community Association (OCA)
Author-email: support@odoo-community.org
License: AGPL-3
Platform: UNKNOWN
Classifier: Programming Language :: Python
Classifier: Framework :: Odoo
Classifier: License :: OSI Approved :: GNU Affero General Public License v3
Requires-Python: ~=2.7
Requires-Dist: odoo10-addon-donation
Requires-Dist: odoo10-addon-mass
Requires-Dist: odoo (<10.1dev,>=10.0)
